JUSU/__init__.py
JUSU/app.py
JUSU/auth.py
JUSU/auth_backends.py
JUSU/auth_cli.py
JUSU/bundle.py
JUSU/cli.py
JUSU/core.py
JUSU/css.py
JUSU/firebase.py
JUSU/privacy.py
JUSU/session_helpers.py
JUSU/storage.py
jusu-0.1.3.dist-info/licenses/LICENSE
jusu-0.1.3.dist-info/METADATA
jusu-0.1.3.dist-info/WHEEL
jusu-0.1.3.dist-info/top_level.txt
jusu-0.1.3.dist-info/RECORD
