Metadata-Version: 2.4
Name: jusu
Version: 0.1.3
Summary: JUSU — lightweight, beginner-friendly Python framework by Francis Jusu for building styled, accessible complex  websites and web apps (HTML/CSS builders, optional FastAPI auth/session helpers, bundling CLI). All in python syntax 
Home-page: https://github.com/Francis589-png/JUSU
Author: Francis Jusu
Author-email: Francis Jusu <jusufrancis08@gmail.com>
License: MIT
Project-URL: Homepage, https://github.com/Francis589-png/JUSU
Project-URL: Docs, https://github.com/Francis589-png/JUSU/tree/main/docs
Project-URL: Course, https://github.com/Francis589-png/JUSU/tree/main/course
Keywords: html,builder,beginner,education
Classifier: Programming Language :: Python :: 3
Classifier: License :: OSI Approved :: MIT License
Classifier: Operating System :: OS Independent
Requires-Python: >=3.10
License-File: LICENSE
Provides-Extra: web
Requires-Dist: fastapi>=0.95; extra == "web"
Requires-Dist: uvicorn[standard]>=0.20; extra == "web"
Requires-Dist: itsdangerous>=2.1; extra == "web"
Provides-Extra: auth
Requires-Dist: PyJWT>=2.0; extra == "auth"
Requires-Dist: passlib[bcrypt]>=1.7; extra == "auth"
Provides-Extra: db
Requires-Dist: sqlmodel>=0.0.8; extra == "db"
Requires-Dist: alembic>=1.8; extra == "db"
Provides-Extra: cli
Requires-Dist: typer[all]; extra == "cli"
Provides-Extra: firebase
Requires-Dist: firebase-admin>=6.0; extra == "firebase"
Dynamic: author
Dynamic: home-page
Dynamic: license-file
Dynamic: requires-python
